.gitignore
AUTHORS.txt
CHANGELOG.rst
LICENSE.txt
README.rst
pyproject.toml
tox.ini
.github/workflows/sdist.yml
.github/workflows/tox.yml
doc/source/changelog.rst
doc/source/conf.py
doc/source/index.rst
doc/source/registry.rst
src/blue_cwl/__init__.py
src/blue_cwl/brain_regions.py
src/blue_cwl/cli.py
src/blue_cwl/connectome.py
src/blue_cwl/constants.py
src/blue_cwl/density_manipulation.py
src/blue_cwl/exceptions.py
src/blue_cwl/hashing.py
src/blue_cwl/model.py
src/blue_cwl/nexus.py
src/blue_cwl/population_utils.py
src/blue_cwl/recipes.py
src/blue_cwl/registering.py
src/blue_cwl/staging.py
src/blue_cwl/statistics.py
src/blue_cwl/testing.py
src/blue_cwl/typing.py
src/blue_cwl/utils.py
src/blue_cwl/validation.py
src/blue_cwl/variant.py
src/blue_cwl.egg-info/PKG-INFO
src/blue_cwl.egg-info/SOURCES.txt
src/blue_cwl.egg-info/dependency_links.txt
src/blue_cwl.egg-info/entry_points.txt
src/blue_cwl.egg-info/requires.txt
src/blue_cwl.egg-info/top_level.txt
src/blue_cwl/core/__init__.py
src/blue_cwl/core/command.py
src/blue_cwl/core/common.py
src/blue_cwl/core/config.py
src/blue_cwl/core/cwl.py
src/blue_cwl/core/cwl_types.py
src/blue_cwl/core/environment.py
src/blue_cwl/core/exceptions.py
src/blue_cwl/core/executor.py
src/blue_cwl/core/parser.py
src/blue_cwl/core/process.py
src/blue_cwl/core/resolve.py
src/blue_cwl/core/types.py
src/blue_cwl/core/validate.py
src/blue_cwl/core/viz.py
src/blue_cwl/core/schemas/commandlinetool.yml
src/blue_cwl/core/schemas/workflow.yml
src/blue_cwl/data/brain_regions.json
src/blue_cwl/data/builderRecipeAllPathways.xml
src/blue_cwl/generators/cell_composition/cell_composition_manipulation/v1/definition.cwl
src/blue_cwl/generators/cell_composition/cell_composition_manipulation/v2/definition.cwl
src/blue_cwl/generators/cell_composition/cell_composition_manipulation/v3/definition.cwl
src/blue_cwl/generators/cell_composition/cell_composition_manipulation/v3/manipulate_cell_composition.cwl
src/blue_cwl/generators/cell_composition/cell_composition_manipulation/v3/register.cwl
src/blue_cwl/generators/cell_composition/cell_composition_manipulation/v3/setup.cwl
src/blue_cwl/generators/cell_composition/cell_composition_manipulation/v3/stage.cwl
