Metadata-Version: 2.1
Name: blue-cwl
Version: 1.0.0
Summary: Common Workflow Language inspired workflow definitions.
Author: Blue Brain Project, EPFL
License: 
Project-URL: Homepage, https://github.com/BlueBrain/blue-cwl
Project-URL: Repository, https://github.com/BlueBrain/blue-cwl
Project-URL: Issues, https://github.com/BlueBrain/blue-cwl/issues
Project-URL: Tracker, https://github.com/BlueBrain/blue-cwl/issues
Classifier: Development Status :: 2 - Pre-Alpha
Classifier: Intended Audience :: Education
Classifier: Intended Audience :: Science/Research
Classifier: Programming Language :: Python
Classifier: Programming Language :: Python :: 3.10
Classifier: Programming Language :: Python :: 3.11
Classifier: Programming Language :: Python :: 3.12
Classifier: Topic :: Scientific/Engineering :: Bio-Informatics
Requires-Python: >=3.10
License-File: LICENSE.txt
License-File: AUTHORS.txt
Requires-Dist: click>=8.0
Requires-Dist: libsonata
Requires-Dist: numpy
Requires-Dist: pandas
Requires-Dist: voxcell
Requires-Dist: joblib
Requires-Dist: entity-management>=1.4.1
Requires-Dist: pyarrow>=3.0.0
Requires-Dist: fz-td-recipe>=0.2.0
Requires-Dist: pydantic
Requires-Dist: morph-tool
Requires-Dist: jsonschema
Requires-Dist: luigi
Requires-Dist: brainbuilder>=0.20.1
Provides-Extra: viz
Requires-Dist: pydot; extra == "viz"
Requires-Dist: matplotlib; extra == "viz"
Provides-Extra: docs
Requires-Dist: blue-cwl[viz]; extra == "docs"
Requires-Dist: sphinx-bluebrain-theme; extra == "docs"
